sereto/__init__.py
sereto/build.py
sereto/config.py
sereto/convert.py
sereto/crypto.py
sereto/enums.py
sereto/exceptions.py
sereto/extract.py
sereto/finding.py
sereto/jinja.py
sereto/keyring.py
sereto/oxipng.py
sereto/parsing.py
sereto/pdf.py
sereto/plot.py
sereto/project.py
sereto/py.typed
sereto/retest.py
sereto/risk.py
sereto/sereto_types.py
sereto/settings.py
sereto/singleton.py
sereto/source_archive.py
sereto/target.py
sereto/utils.py
sereto/cli/__init__.py
sereto/cli/aliases.py
sereto/cli/cli.py
sereto/cli/commands.py
sereto/cli/config.py
sereto/cli/date.py
sereto/cli/finding.py
sereto/cli/person.py
sereto/cli/target.py
sereto/cli/utils.py
sereto/models/__init__.py
sereto/models/base.py
sereto/models/config.py
sereto/models/date.py
sereto/models/finding.py
sereto/models/locator.py
sereto/models/person.py
sereto/models/settings.py
sereto/models/target.py
sereto/models/version.py
sereto/tui/__init__.py
sereto/tui/finding.py
sereto/tui/finding.tcss
sereto/tui/widgets/input.py
sereto-0.5.0.dist-info/METADATA
sereto-0.5.0.dist-info/WHEEL
sereto-0.5.0.dist-info/entry_points.txt
sereto-0.5.0.dist-info/licenses/LICENSE
sereto-0.5.0.dist-info/RECORD
