Metadata-Version: 2.4
Name: sereto
Version: 0.5.0
Summary: Security Reporting Tool.
Project-URL: Changelog, https://github.com/s3r3t0/sereto/blob/main/CHANGELOG.md
Project-URL: Documentation, https://sereto.s4n.cz
Project-URL: Homepage, https://github.com/s3r3t0/sereto
Project-URL: Source, https://github.com/s3r3t0/sereto
Author-email: Tomáš Stefan <t@s4n.cz>
License:                     GNU GENERAL PUBLIC LICENSE
License-File: LICENSE
Keywords: automate,markdown,pandocfilters,pdf,penetration testing,pentest,report,tex
Classifier: Development Status :: 4 - Beta
Classifier: Environment :: Console
Classifier: Framework :: Pydantic
Classifier: Framework :: Pydantic :: 2
Classifier: Framework :: Pytest
Classifier: Framework :: tox
Classifier: Intended Audience :: Information Technology
Classifier: License :: OSI Approved :: GNU General Public License v3 (GPLv3)
Classifier: Natural Language :: English
Classifier: Operating System :: OS Independent
Classifier: Programming Language :: Python
Classifier: Programming Language :: Python :: 3
Classifier: Programming Language :: Python :: 3 :: Only
Classifier: Programming Language :: Python :: 3.12
Classifier: Programming Language :: Python :: 3.13
Classifier: Programming Language :: Python :: 3.14
Classifier: Programming Language :: Python :: Implementation :: CPython
Classifier: Topic :: Security
Classifier: Topic :: Text Processing
Classifier: Topic :: Text Processing :: Markup
Classifier: Topic :: Text Processing :: Markup :: LaTeX
Classifier: Topic :: Text Processing :: Markup :: Markdown
Classifier: Typing :: Typed
Requires-Python: >=3.12
Requires-Dist: annotated-types~=0.7.0
Requires-Dist: click~=8.1.7
Requires-Dist: cryptography~=46.0.1
Requires-Dist: humanize~=4.14.0
Requires-Dist: jinja2~=3.1.4
Requires-Dist: keyrings-alt~=5.0.2
Requires-Dist: keyring~=25.6.0
Requires-Dist: matplotlib~=3.10.0
Requires-Dist: pandocfilters~=1.5.1
Requires-Dist: pathspec>=0.12.1
Requires-Dist: prompt-toolkit~=3.0.50
Requires-Dist: pydantic-settings~=2.11.0
Requires-Dist: pydantic[email]
Requires-Dist: pydantic~=2.12.4
Requires-Dist: pypdf~=6.1.0
Requires-Dist: python-frontmatter~=1.1.0
Requires-Dist: rapidfuzz~=3.14.0
Requires-Dist: rich~=14.2.0
Requires-Dist: semver~=3.0.2
Requires-Dist: sereto-repl~=0.3.1
Requires-Dist: textual~=6.5.0
Requires-Dist: toml>=0.10.2
Requires-Dist: tomlkit~=0.13.3
Provides-Extra: dev
Requires-Dist: textual-dev; extra == 'dev'
Provides-Extra: docs
Requires-Dist: mike; extra == 'docs'
Requires-Dist: mkdocs-material; extra == 'docs'
Requires-Dist: mkdocstrings[python]; extra == 'docs'
Requires-Dist: ruff; extra == 'docs'
